{"type": "FeatureCollection", "features": [{"id": "15888", "type": "Feature", "properties": {"CODIGO_CONCAT": "BOYACÁ-PAZ DE RÍO", "DPTO_CCDGO": "15", "DPTO_CNMBR": "BOYACÁ", "MPIO_CDPMP": "15537", "MPIO_CNMBR": "PAZ DE RÍO", "area_terre": 6231.92479456, "concat_terreno": "{B664AEEF-153D-49FE-926C-64BBC8E8281B}_BOYACÁ-PAZ DE RÍO", "conteo_asi": 0, "estado": "LEVANTAMIENTO", "qr_opera_1": "1575700127"}, "geometry": {"type": "Polygon", "coordinates": [[[-72.71329, 6.00092], [-72.71328, 6.00091], [-72.71331, 6.00088], [-72.71329, 6.00092]]]}}, {"id": "15889", "type": "Feature", "properties": {"CODIGO_CONCAT": "BOYACÁ-PAZ DE RÍO", "DPTO_CCDGO": "15", "DPTO_CNMBR": "BOYACÁ", "MPIO_CDPMP": "15537", "MPIO_CNMBR": "PAZ DE RÍO", "area_terre": 4190.61706311, "concat_terreno": "{A128BFA3-2383-41B7-8584-C6435040F680}_BOYACÁ-PAZ DE RÍO", "conteo_asi": 0, "estado": "LEVANTAMIENTO", "qr_opera_1": "1575705866"}, "geometry": {"type": "Polygon", "coordinates": [[[-72.71135, 6.00318], [-72.71111, 6.00329], [-72.71109, 6.00332], [-72.71093, 6.00315], [-72.71087, 6.00307], [-72.71085, 6.00306], [-72.7111, 6.00284], [-72.71113, 6.00285], [-72.71115, 6.00286], [-72.71122, 6.0029], [-72.71131, 6.00294], [-72.71147, 6.00306], [-72.71135, 6.00318]]]}}, {"id": "15890", "type": "Feature", "properties": {"CODIGO_CONCAT": "BOYACÁ-PAZ DE RÍO", "DPTO_CCDGO": "15", "DPTO_CNMBR": "BOYACÁ", "MPIO_CDPMP": "15537", "MPIO_CNMBR": "PAZ DE RÍO", "area_terre": 2998.51987852, "concat_terreno": "{400C814E-C35D-4CFE-8829-2A7D2225E83A}_BOYACÁ-PAZ DE RÍO", "conteo_asi": 0, "estado": "LEVANTAMIENTO", "qr_opera_1": "1575705874"}, "geometry": {"type": "Polygon", "coordinates": [[[-72.71075, 6.00331], [-72.71065, 6.00324], [-72.71085, 6.00306], [-72.71087, 6.00307], [-72.71093, 6.00315], [-72.71109, 6.00332], [-72.71104, 6.00338], [-72.71097, 6.0034], [-72.71094, 6.00336], [-72.71092, 6.00331], [-72.71089, 6.0033], [-72.71087, 6.0033], [-72.71084, 6.00331], [-72.71083, 6.00332], [-72.71084, 6.00333], [-72.71079, 6.00335], [-72.71075, 6.00331]]]}}, {"id": "15891", "type": "Feature", "properties": {"CODIGO_CONCAT": "BOYACÁ-PAZ DE RÍO", "DPTO_CCDGO": "15", "DPTO_CNMBR": "BOYACÁ", "MPIO_CDPMP": "15537", "MPIO_CNMBR": "PAZ DE RÍO", "area_terre": 12076.8467649, "concat_terreno": "{E4B877C9-88BC-4356-ACA2-753C1543F83B}_BOYACÁ-PAZ DE RÍO", "conteo_asi": 0, "estado": "LEVANTAMIENTO", "qr_opera_1": "1575700161"}, "geometry": {"type": "Polygon", "coordinates": [[[-72.7098, 6.004], [-72.71065, 6.00324], [-72.71075, 6.00331], [-72.71079, 6.00335], [-72.71068, 6.00339], [-72.71052, 6.00344], [-72.71044, 6.00349], [-72.71026, 6.0036], [-72.71012, 6.00375], [-72.71, 6.00385], [-72.70992, 6.00391], [-72.7099, 6.00392], [-72.70985, 6.00397], [-72.70982, 6.00404], [-72.7098, 6.004]]]}}]}