{"type": "FeatureCollection", "features": [{"id": "21820", "type": "Feature", "properties": {"CODIGO_CONCAT": "CAUCA-SILVIA", "DPTO_CCDGO": "19", "DPTO_CNMBR": "CAUCA", "MPIO_CDPMP": "19743", "MPIO_CNMBR": "SILVIA", "area_terre": 41378.5963827, "concat_terreno": "{B40AAF50-F575-46F0-9BCE-ABA1D79A82FE}_CAUCA-SILVIA", "conteo_asi": 0, "estado": "LEVANTAMIENTO", "qr_opera_1": "1982400159"}, "geometry": {"type": "Polygon", "coordinates": [[[-76.43091, 2.54773], [-76.4306, 2.54776], [-76.43049, 2.54771], [-76.43091, 2.54773], [-76.43091, 2.54773]]]}}, {"id": "21821", "type": "Feature", "properties": {"CODIGO_CONCAT": "CAUCA-SILVIA", "DPTO_CCDGO": "19", "DPTO_CNMBR": "CAUCA", "MPIO_CDPMP": "19743", "MPIO_CNMBR": "SILVIA", "area_terre": 34502.943215, "concat_terreno": "{B0479AA3-8304-4520-8F90-BA73376CF4C9}_CAUCA-SILVIA", "conteo_asi": 0, "estado": "LEVANTAMIENTO", "qr_opera_1": "1982400227"}, "geometry": {"type": "Polygon", "coordinates": [[[-76.43454, 2.55244], [-76.43487, 2.55315], [-76.43456, 2.55318], [-76.43425, 2.55252], [-76.43454, 2.55244]]]}}, {"id": "21822", "type": "Feature", "properties": {"CODIGO_CONCAT": "CAUCA-SILVIA", "DPTO_CCDGO": "19", "DPTO_CNMBR": "CAUCA", "MPIO_CDPMP": "19743", "MPIO_CNMBR": "SILVIA", "area_terre": 92516.5149721, "concat_terreno": "{857FF96A-8704-4C10-83AA-416FD6EDE5C7}_CAUCA-SILVIA", "conteo_asi": 0, "estado": "LEVANTAMIENTO", "qr_opera_1": "1982400168"}, "geometry": {"type": "Polygon", "coordinates": [[[-76.43472, 2.55379], [-76.43456, 2.55318], [-76.43487, 2.55315], [-76.43599, 2.5556], [-76.4359, 2.55566], [-76.43564, 2.55582], [-76.43556, 2.55565], [-76.43541, 2.55546], [-76.43528, 2.55532], [-76.4352, 2.55511], [-76.43515, 2.55487], [-76.43518, 2.5547], [-76.43513, 2.55456], [-76.43503, 2.55426], [-76.43472, 2.55379]]]}}]}